nonebot_plugin_tsugu_bangdream_bot-0.4.6.dist-info/METADATA
nonebot_plugin_tsugu_bangdream_bot-0.4.6.dist-info/WHEEL
nonebot_plugin_tsugu_bangdream_bot-0.4.6.dist-info/entry_points.txt
nonebot_plugin_tsugu_bangdream_bot-0.4.6.dist-info/licenses/LICENSE
nonebot_plugin_tsugu_bangdream_bot/__init__.py
nonebot_plugin_tsugu_bangdream_bot/_client.py
nonebot_plugin_tsugu_bangdream_bot/_commands.py
nonebot_plugin_tsugu_bangdream_bot/_utils.py
nonebot_plugin_tsugu_bangdream_bot/config.py
nonebot_plugin_tsugu_bangdream_bot-0.4.6.dist-info/RECORD
