Metadata-Version: 2.1
Name: nonebot-plugin-tsugu-bangdream-bot
Version: 0.4.6
Summary: Koishi-Plugin-Tsugu-BanGDream-Bot 的 NoneBot2 实现
Author-Email: WindowsSov8forUs <qwertyuiop2333@hotmail.com>
License: MIT
Requires-Python: >=3.8
Requires-Dist: nonebot2>=2.2.1
Requires-Dist: nonebot-plugin-alconna<0.59.0,>=0.46.1
Requires-Dist: tsugu-api-python<2.0.0,>=1.5.6
Requires-Dist: nonebot-plugin-userinfo>=0.2.4
